[
  {
    "序号": 4195,
    "单词": "valley",
    "音标": "/ˈvæli/",
    "释义": "n. 山谷；流域；溪谷n. (Valley)人名；(英)瓦利；(法)瓦莱"
  },
  {
    "序号": 2768,
    "单词": "pit",
    "音标": "/pɪt/",
    "释义": "n.深坑,深渊,陷阱,(物体或人体表面上的)凹陷,(英国剧场的)正厅后排、正厅后排的观众vt.窖藏,使凹下,去...之核,使留疤痕,使竞争vi.起凹点,凹陷"
  },
  {
    "序号": 4174,
    "单词": "urge",
    "音标": "/ɜːrdʒ/",
    "释义": "vt. 力劝，催促；驱策，推进n. 强烈的欲望，迫切要求；推动力vi. 强烈要求"
  },
  {
    "序号": 3416,
    "单词": "shadow",
    "音标": "/ˈʃædoʊ/",
    "释义": "n. 阴影；影子；幽灵；庇护；隐蔽处vt. 遮蔽；使朦胧；尾随；预示vi. 变阴暗adj. 影子内阁的"
  },
  {
    "序号": 1875,
    "单词": "hospital",
    "音标": "/ˈhɑːspɪtl/",
    "释义": "n. 医院n. (Hospital)人名；(英)霍斯皮特尔"
  },
  {
    "序号": 2410,
    "单词": "microscope",
    "音标": "/ˈmaɪkrəskoʊp/",
    "释义": "n. 显微镜"
  },
  {
    "序号": 61,
    "单词": "adapt",
    "音标": "/əˈdæpt/",
    "释义": "vt. 使适应；改编vi. 适应"
  },
  {
    "序号": 2092,
    "单词": "journalist",
    "音标": "/ˈdʒɜːrnəlɪst/",
    "释义": "n. 新闻工作者；报人；记日志者"
  },
  {
    "序号": 1404,
    "单词": "extremely",
    "音标": "/ɪkˈstriːmli/",
    "释义": "adv. 非常，极其；极端地"
  },
  {
    "序号": 1542,
    "单词": "forbid",
    "音标": "/fərˈbɪd/",
    "释义": "vt. 禁止；不准；不允许；〈正式〉严禁"
  },
  {
    "序号": 4040,
    "单词": "transistor",
    "音标": "/trænˈzɪstə(r)/",
    "释义": "n. 晶体管（收音机）"
  },
  {
    "序号": 2594,
    "单词": "nothing",
    "音标": "/ˈnʌθɪŋ/",
    "释义": "pron. 没有什么；无关紧要的东西；（计算机数量上的）零；不值钱adv. 毫不；绝不n. 无；零；无关紧要的事adj. 没前途的；没价值的"
  },
  {
    "序号": 629,
    "单词": "check",
    "音标": "/tʃek/",
    "释义": "vt. 检查，核对；制止，抑制；在…上打勾；托运vi. 核实，查核；中止；打勾；[象棋]将一军n. 美支票；制止，抑制；检验，核对n. （英）切克（人名）"
  },
  {
    "序号": 4306,
    "单词": "weigh",
    "音标": "/weɪ/",
    "释义": "vt. 权衡；考虑；称…重量vi. 重量为…；具有重要性；成为…的重荷；起锚n. 权衡；称重量"
  },
  {
    "序号": 1521,
    "单词": "flow",
    "音标": "/floʊ/",
    "释义": "n.流程,流动,(河水)泛滥,洋溢vi.流动,涌流,川流不息,飘扬vt.溢过,淹没"
  },
  {
    "序号": 3979,
    "单词": "tiny",
    "音标": "/ˈtaɪni/",
    "释义": "adj. 微小的；很少的n. (Tiny)人名；(葡、印)蒂尼"
  },
  {
    "序号": 3316,
    "单词": "Saturday",
    "音标": "/'sætədei/",
    "释义": "n. 星期六"
  },
  {
    "序号": 3639,
    "单词": "spoil",
    "音标": "/spɔɪl/",
    "释义": "vt. 溺爱；糟蹋；破坏；掠夺vi. 掠夺；变坏；腐败n. 次品；奖品"
  },
  {
    "序号": 1430,
    "单词": "far",
    "音标": "/fɑːr/",
    "释义": "adv. 很；遥远地；久远地；到很远的距离；到很深的程度adj. 远的；久远的n. 远方n. (Far)人名；(德、西、塞)法尔"
  },
  {
    "序号": 4139,
    "单词": "unhappy",
    "音标": "/ʌnˈhæpi/",
    "释义": "adj. 不快乐的；不幸福的；不适当的"
  },
  {
    "序号": 780,
    "单词": "comrade",
    "音标": "/ˈkɑːmræd/",
    "释义": "n. 同志；伙伴n. (Comrade)人名；(尼日利)科姆拉德"
  },
  {
    "序号": 4161,
    "单词": "unsuitable",
    "音标": "/ʌnˈsuːtəbl/",
    "释义": "adj. 不适合的；不适宜的；不相称的"
  },
  {
    "序号": 3222,
    "单词": "riddle",
    "音标": "/ˈrɪdl/",
    "释义": "n.谜,谜语,神秘人物v.解谜,出谜,迷惑"
  },
  {
    "序号": 3597,
    "单词": "southeast",
    "音标": "/ˌsaʊθˈiːst/",
    "释义": "n. 东南，东南方；东南地区，东南部adj. 东南的，东南部的；（风）来自东南的adv. 在东南，朝东南；来自东南"
  },
  {
    "序号": 4422,
    "单词": "youthful",
    "音标": "/ˈjuːθfl/",
    "释义": "adj. 年轻的；早期的"
  },
  {
    "序号": 4329,
    "单词": "whip",
    "音标": "/wɪp/",
    "释义": "n.鞭子,车夫v.鞭打,抽打,突然移动"
  },
  {
    "序号": 3971,
    "单词": "tiger",
    "音标": "/ˈtaɪɡər/",
    "释义": "n. 老虎；凶暴的人n. (Tiger)人名；(英)泰格；(法)蒂热；(瑞典)蒂格"
  },
  {
    "序号": 572,
    "单词": "carriage",
    "音标": "/ˈkærɪdʒ/",
    "释义": "n. 运输；运费；四轮马车；举止；客车厢"
  },
  {
    "序号": 3029,
    "单词": "rainbow",
    "音标": "/ˈreɪnboʊ/",
    "释义": "n. 彩虹；五彩缤纷的排列；幻想adj. 五彩缤纷的；彩虹状的vt. 使呈彩虹状；如彩虹般装饰vi. 呈彩虹状n. (Rainbow)人名；(英)雷恩博"
  },
  {
    "序号": 815,
    "单词": "consciousness",
    "音标": "/ˈkɑːnʃəsnəs/",
    "释义": "n. 意识；知觉；觉悟；感觉"
  },
  {
    "序号": 4034,
    "单词": "tram",
    "音标": "/træm/",
    "释义": "n. 电车轨道；煤车vt. 用煤车运载vi. 乘电车"
  },
  {
    "序号": 4411,
    "单词": "yell",
    "音标": "/jel/",
    "释义": "vi. 大叫，叫喊n. 喊声，叫声vt. 喊叫着说"
  },
  {
    "序号": 3248,
    "单词": "role",
    "音标": "/roʊl/",
    "释义": "n. 角色；任务n. (Role)人名；(意、塞、赤几)罗莱"
  },
  {
    "序号": 1074,
    "单词": "difficulty",
    "音标": "/ˈdɪfɪkəlti/",
    "释义": "n. 困难，困境"
  },
  {
    "序号": 2809,
    "单词": "Polish",
    "音标": "/ˈpɑːlɪʃ/",
    "释义": "adj. 波兰的n. 波兰人；波兰语"
  },
  {
    "序号": 3996,
    "单词": "tomorrow",
    "音标": "/təˈmɑːroʊ/",
    "释义": "adv. 在明天，在明日；在未来n. 明天，明日； 未来，来日（尤指不久的将来）"
  },
  {
    "序号": 2168,
    "单词": "launch",
    "音标": "/lɔːntʃ/",
    "释义": "v. 发射（导弹、火箭等）；发起，发动；使……下水；开始；起飞n. 发射；发行，投放市场；下水；汽艇"
  },
  {
    "序号": 3285,
    "单词": "rust",
    "音标": "/rʌst/",
    "释义": "n. 锈；生锈；[植保] 锈病vt. 使生锈；腐蚀vi. 生锈；成铁锈色；变迟钝n. (Rust)人名；(英)拉斯特；(德、捷、瑞典)鲁斯特；(法)吕斯特"
  },
  {
    "序号": 4211,
    "单词": "veil",
    "音标": "/veɪl/",
    "释义": "n. 面纱；面罩；遮蔽物；托词vt. 遮蔽；掩饰；以面纱遮掩；用帷幕分隔vi. 蒙上面纱；出现轻度灰雾n. (Veil)人名；(法)韦伊；(德)法伊尔"
  },
  {
    "序号": 13,
    "单词": "absorb",
    "音标": "/əbˈzɔːb/",
    "释义": "vt. 吸收；吸引；承受；理解；使…全神贯注"
  },
  {
    "序号": 2991,
    "单词": "quart",
    "音标": "/kwɔːrt/",
    "释义": "n. 夸脱（容量单位）；一夸脱的容器"
  },
  {
    "序号": 2142,
    "单词": "ladder",
    "音标": "/ˈlædər/",
    "释义": "n. 阶梯；途径；梯状物vi. 成名；发迹vt. 在……上装设梯子"
  },
  {
    "序号": 2133,
    "单词": "know",
    "音标": "/noʊ/",
    "释义": "vt. 知道；认识；懂得vi. 了解；熟悉；确信"
  },
  {
    "序号": 775,
    "单词": "compress",
    "音标": "/kəmˈpres/",
    "释义": "vi. 受压缩小vt. 压缩，压紧；精简"
  },
  {
    "序号": 1854,
    "单词": "hole",
    "音标": "/hoʊl/",
    "释义": "n. 洞，孔；洞穴，穴；突破口vi. 凿洞，穿孔；（高尔夫球等）进洞vt. 凿洞n. (Hole)人名；(瑞典、挪)霍勒；(英)霍尔"
  },
  {
    "序号": 78,
    "单词": "adventure",
    "音标": "/ədˈventʃər/",
    "释义": "n. 冒险；冒险精神；投机活动vt. 冒险；大胆说出vi. 冒险"
  },
  {
    "序号": 1292,
    "单词": "ensure",
    "音标": "/ɪnˈʃʊr/",
    "释义": "vt. 保证，确保；使安全"
  },
  {
    "序号": 2108,
    "单词": "keen",
    "音标": "/kiːn/",
    "释义": "adj. 敏锐的，敏捷的；渴望的；强烈的；热心的；锐利的n. 痛哭，挽歌n. (Keen)人名；(英)基恩；(德)肯；(肯)金"
  },
  {
    "序号": 829,
    "单词": "construct",
    "音标": "/kənˈstrʌkt/",
    "释义": "vt.建造,构造,创立"
  },
  {
    "序号": 2110,
    "单词": "keeper",
    "音标": "/ˈkiːpər/",
    "释义": "n. 监护人；饲养员；看守人；管理人"
  }
]