[
  {
    "序号": 148,
    "单词": "analyse",
    "音标": "/ˈænəlaɪz/",
    "释义": "vt. 分析；分解；细察"
  },
  {
    "序号": 3792,
    "单词": "sunlight",
    "音标": "/ˈsʌnlaɪt/",
    "释义": "n. 日光n. (Sunlight)人名；(英)森莱特"
  },
  {
    "序号": 376,
    "单词": "berry",
    "音标": "/ˈberi/",
    "释义": "n. 浆果（葡萄，番茄等）vi. 采集浆果n. (Berry)人名；(法、英、德、意、葡)贝里；(匈)拜里"
  },
  {
    "序号": 648,
    "单词": "chimney",
    "音标": "/ˈtʃɪmni/",
    "释义": "n. 烟囱"
  },
  {
    "序号": 1155,
    "单词": "downward",
    "音标": "/ˈdaʊnwərd/",
    "释义": "adj. 向下的，下降的adv. 向下"
  },
  {
    "序号": 3508,
    "单词": "sketch",
    "音标": "/sketʃ/",
    "释义": "n. 素描；略图；梗概vt. 画素描或速写vi. 画素描或速写n. (Sketch)人名；(英)斯凯奇"
  },
  {
    "序号": 2724,
    "单词": "overseas",
    "音标": "/ˌoʊvərˈsiːz/",
    "释义": "adv. 在海外，向国外adj. 海外的，国外的"
  },
  {
    "序号": 3794,
    "单词": "sunrise",
    "音标": "/ˈsʌnraɪz/",
    "释义": "n. 日出；黎明n. (Sunrise)人名；(德)松里泽"
  },
  {
    "序号": 487,
    "单词": "broom",
    "音标": "/bruːm/",
    "释义": "n. 扫帚；金雀花；飞天扫帚（出自《哈利·波特》）vt. 扫除vi. 桩顶开花或开裂n. （Broom）（英）布鲁姆（人名）"
  },
  {
    "序号": 1912,
    "单词": "ignore",
    "音标": "/ɪɡˈnɔːr/",
    "释义": "vt. 驳回诉讼；忽视；不理睬"
  },
  {
    "序号": 2862,
    "单词": "precise",
    "音标": "/prɪˈsaɪs/",
    "释义": "adj. 精确的；明确的；严格的"
  },
  {
    "序号": 4375,
    "单词": "woman",
    "音标": "/ˈwʊmən/",
    "释义": "n. 妇女；女性；成年女子"
  },
  {
    "序号": 3408,
    "单词": "seventh",
    "音标": "/ˈsevnθ/",
    "释义": " num.第七"
  },
  {
    "序号": 3958,
    "单词": "through",
    "音标": "/θruː/",
    "释义": " prep.穿过,通过,从开始到结束,经由,以adv.从头到尾,自始至终,直达地,彻底,完全adj.直达的,直通的"
  },
  {
    "序号": 2975,
    "单词": "pure",
    "音标": "/pjʊr/",
    "释义": "adj. 纯的；纯粹的；纯洁的；清白的；纯理论的n. (Pure)人名；(俄)普雷"
  },
  {
    "序号": 3739,
    "单词": "strictly",
    "音标": "/ˈstrɪktli/",
    "释义": "adv. 严格地；完全地；确实地"
  },
  {
    "序号": 1861,
    "单词": "honey",
    "音标": "/ˈhʌni/",
    "释义": "n. 蜂蜜；宝贝；甜蜜adj. 甘美的；蜂蜜似的vt. 对…说甜言蜜语；加蜜使甜vi. 奉承；说甜言蜜语n. (Honey)人名；(英)霍尼"
  },
  {
    "序号": 4315,
    "单词": "wet",
    "音标": "/wet/",
    "释义": "adj. [气象][物] 潮湿的；有雨的n. 雨天；湿气vt. 弄湿vi. 变湿n. (Wet)人名；(英、纳米、南非)韦特"
  },
  {
    "序号": 2256,
    "单词": "liver",
    "音标": "/ˈlɪvər/",
    "释义": "n. 肝脏；生活者，居民"
  },
  {
    "序号": 4204,
    "单词": "variety",
    "音标": "/vəˈraɪəti/",
    "释义": "n. 多样；种类；杂耍；变化，多样化"
  },
  {
    "序号": 660,
    "单词": "church",
    "音标": "/tʃɜːrtʃ/",
    "释义": "n. 教堂；礼拜；教派adj. 教会的；礼拜的vt. 领…到教堂接受宗教仪式n. (Church)人名；(英)丘奇"
  },
  {
    "序号": 2234,
    "单词": "limb",
    "音标": "/lɪm/",
    "释义": "n. 肢，臂；分支；枝干vt. 切断…的手足；从…上截下树枝n. (Limb)人名；(朝)林；(英)利姆"
  },
  {
    "序号": 4283,
    "单词": "wave",
    "音标": "/weɪv/",
    "释义": "v. 挥手；挥手示意；挥舞；飘扬；使（头发）略呈波形n. 海浪；心潮；涌现的人（或物）；挥手；波；（头发）卷曲；（感情）爆发"
  },
  {
    "序号": 3311,
    "单词": "sandy",
    "音标": "/ˈsændi/",
    "释义": "adj. 沙地的；多沙的；含沙的n. (Sandy)人名；(法、喀、罗、西、英)桑迪(教名Alasdair、Alastair、Alexander、Alister、Elshender的昵称)"
  },
  {
    "序号": 2558,
    "单词": "neutral",
    "音标": "/ˈnuːtrəl/",
    "释义": "adj. 中立的，中性的；中立国的；非彩色的n. 中立国；中立者；非彩色；齿轮的空档"
  },
  {
    "序号": 120,
    "单词": "all",
    "音标": "/ɔːl/",
    "释义": "adj.全部的,所有的,整个的adv.完全,更加,越发 pron.全部"
  },
  {
    "序号": 2431,
    "单词": "minority",
    "音标": "/maɪˈnɔːrəti/",
    "释义": "n. 少数民族；少数派；未成年"
  },
  {
    "序号": 2293,
    "单词": "lucky",
    "音标": "/ˈlʌki/",
    "释义": "adj. 幸运的；侥幸的"
  },
  {
    "序号": 614,
    "单词": "chamber",
    "音标": "/ˈtʃeɪmbər/",
    "释义": "n. （身体或器官内的）室，膛；房间；会所adj. 室内的；私人的，秘密的vt. 把…关在室内；装填（弹药等）n. (Chamber)人名；(英)钱伯"
  },
  {
    "序号": 668,
    "单词": "circumstance",
    "音标": "/ˈsɜːrkəmstæns/",
    "释义": "n. 环境；状况；境遇；（尤指）经济状况；命运vt. 处于某种情况"
  },
  {
    "序号": 1187,
    "单词": "dump",
    "音标": "/dʌmp/",
    "释义": "vt.倾倒(垃圾),倾卸n.堆存处"
  },
  {
    "序号": 3183,
    "单词": "resource",
    "音标": "/rɪˈsɔːs/",
    "释义": "n. 资源，财力；办法；智谋vi. 向...提供资金"
  },
  {
    "序号": 4215,
    "单词": "verb",
    "音标": "/vɜːrb/",
    "释义": "n. 动词；动词词性；动词性短语或从句n. (Verb) （俄）韦尔布（人名）"
  },
  {
    "序号": 2237,
    "单词": "limitation",
    "音标": "/ˌlɪmɪˈteɪʃn/",
    "释义": "n. 限制；限度；极限；追诉时效；有效期限；缺陷"
  },
  {
    "序号": 4048,
    "单词": "trap",
    "音标": "/træp/",
    "释义": "n.圈套,陷阱,诡计,活板门,存水弯,汽水闸,(双轮)轻便马车vi.设圈套,设陷阱vt.诱捕,诱骗,计捉,设陷,坑害,使受限制"
  },
  {
    "序号": 3137,
    "单词": "remains",
    "音标": "/rɪˈmeɪnz/",
    "释义": "n. 残余物，剩饭菜；古迹，遗迹；遗骸v. 保持（remain 的第三人称单数）"
  },
  {
    "序号": 3136,
    "单词": "remain",
    "音标": "/rɪˈmeɪn/",
    "释义": "vi. 保持；依然；留下；剩余；逗留；残存n. 废语留待；余留"
  },
  {
    "序号": 694,
    "单词": "cloak",
    "音标": "/kloʊk/",
    "释义": "n.斗蓬,宽大外衣,掩护vt.用外衣遮蔽,披斗篷"
  },
  {
    "序号": 3075,
    "单词": "recognize",
    "音标": "/ˈrekəɡnaɪz/",
    "释义": "vt. 认出，识别；承认；接受，认可；赞赏vi. 确认，承认；具结"
  },
  {
    "序号": 2196,
    "单词": "legal",
    "音标": "/ˈliːɡl/",
    "释义": "adj. 法律的；合法的；法定的；依照法律的n. （Legal）（法）勒加尔（人名）"
  },
  {
    "序号": 321,
    "单词": "barrel",
    "音标": "/ˈbærəl/",
    "释义": "n. 桶； 一桶（的量）；枪管，炮管；（马等四足动物的）躯干v. 快速移动；把……装入桶内n. (Barrel) （法、意）巴雷尔（人名）"
  },
  {
    "序号": 3327,
    "单词": "scarce",
    "音标": "/skers/",
    "释义": "adj. 缺乏的，不足的；稀有的adv. 仅仅；几乎不；几乎没有"
  },
  {
    "序号": 2873,
    "单词": "prepare",
    "音标": "/prɪˈper/",
    "释义": "vt. 准备；使适合；装备；起草vi. 预备；做好思想准备"
  },
  {
    "序号": 491,
    "单词": "bruise",
    "音标": "/bruːz/",
    "释义": "n. 擦伤；挫伤；青肿vt. 使受瘀伤；使受挫伤vi. 擦伤；受伤"
  },
  {
    "序号": 3199,
    "单词": "restriction",
    "音标": "/rɪˈstrɪkʃn/",
    "释义": "n. 限制；约束；束缚"
  },
  {
    "序号": 3028,
    "单词": "rain",
    "音标": "/reɪn/",
    "释义": "n. 雨；下雨；雨天；雨季vi. 下雨；降雨vt. 大量地给；使大量落下n. (Rain)人名；(法)兰；(英)雷恩；(罗、捷)赖恩"
  },
  {
    "序号": 505,
    "单词": "bundle",
    "音标": "/ˈbʌndl/",
    "释义": "n. 束；捆vt. 捆vi. 匆忙离开"
  },
  {
    "序号": 710,
    "单词": "coast",
    "音标": "/koʊst/",
    "释义": "n. 海岸；滑行v. 滑行；（交通工具）快速平稳地移动；得过且过，做事不费力；沿岸航行v. (Coast) （英、美）科斯特（人名）"
  },
  {
    "序号": 4033,
    "单词": "traitor",
    "音标": "/ˈtreɪtər/",
    "释义": "n. 叛徒；卖国贼；背信弃义的人"
  },
  {
    "序号": 3276,
    "单词": "ruin",
    "音标": "/ˈruːɪn/",
    "释义": "v.(使)破产,(使)堕落,毁灭n.毁灭,崩溃,(pl.) 废墟,遗迹"
  }
]