[
  {
    "序号": 4318,
    "单词": "wheat",
    "音标": "/wiːt/",
    "释义": "n. 小麦；小麦色n. (Wheat)人名；(英)惠特"
  },
  {
    "序号": 1527,
    "单词": "fly",
    "音标": "/flaɪ/",
    "释义": "vi. 飞；驾驶飞机；飘扬vt. 飞行；飞越；使飘扬n. 飞行；苍蝇；两翼昆虫adj. 敏捷的n. (Fly)人名；(法)弗利；(英)弗莱"
  },
  {
    "序号": 2304,
    "单词": "magic",
    "音标": "/ˈmædʒɪk/",
    "释义": "n.魔法,巫术,戏法adj.魔术的,有魔力的,不可思议的"
  },
  {
    "序号": 137,
    "单词": "amaze",
    "音标": "/əˈmeɪz/",
    "释义": "vt. 使吃惊"
  },
  {
    "序号": 1669,
    "单词": "glitter",
    "音标": "/ˈɡlɪtər/",
    "释义": "v. 闪光；闪烁n. 闪光；灿烂；华而不实；（眼中的）光亮"
  },
  {
    "序号": 2345,
    "单词": "master",
    "音标": "/ˈmæstər/",
    "释义": "n.主人,雇主,(男)教师,熟练技工,师傅,大师,硕士,称呼少爷adj.主人的,熟练的,高明的,主要的vt.征服,控制,精通"
  },
  {
    "序号": 3598,
    "单词": "southern",
    "音标": "/ˈsʌðərn/",
    "释义": "adj. 南的；南方的n. 南方人n. (Southern)人名；(英)萨瑟恩"
  },
  {
    "序号": 1317,
    "单词": "establish",
    "音标": "/ɪˈstæblɪʃ/",
    "释义": "v. 建立，创立；确立；获得接受；查实，证实"
  },
  {
    "序号": 1015,
    "单词": "demand",
    "音标": "/dɪˈmænd/",
    "释义": "n. （坚决的或困难的）要求；（顾客的）需求v. 强烈要求；需要；逼问；查问，查询n. (Demand) （德）德曼德（人名）"
  },
  {
    "序号": 600,
    "单词": "centimetre",
    "音标": "/ˈsentɪmiːtər/",
    "释义": "n. 厘米；公分"
  },
  {
    "序号": 673,
    "单词": "civilize",
    "音标": "/ˈsɪvəlaɪz/",
    "释义": "vt. 使文明；教化；使开化vi. 变得文明"
  },
  {
    "序号": 3370,
    "单词": "seed",
    "音标": "/siːd/",
    "释义": "n. 种子；根据；精液；萌芽；子孙；原由vt. 播种；结实；成熟；去…籽vi. 播种；（植物）结实n. (Seed)人名；(英)锡德"
  },
  {
    "序号": 187,
    "单词": "appetite",
    "音标": "/ˈæpɪtaɪt/",
    "释义": "n. 食欲；嗜好"
  },
  {
    "序号": 2148,
    "单词": "lamp",
    "音标": "/læmp/",
    "释义": "n. 灯；照射器vt. 照亮vi. 发亮n. (Lamp)人名；(英、德、匈、瑞典)兰普"
  },
  {
    "序号": 2720,
    "单词": "overcome",
    "音标": "/ˌoʊvərˈkʌm/",
    "释义": "vt. 克服；胜过vi. 克服；得胜"
  },
  {
    "序号": 1410,
    "单词": "factory",
    "音标": "/ˈfæktri,ˈfæktəri/",
    "释义": "n. 工厂；制造厂；代理店"
  },
  {
    "序号": 2282,
    "单词": "loud",
    "音标": "/laʊd/",
    "释义": "adj. 大声的，高声的；不断的；喧吵的adv. 大声地，高声地，响亮地n. (Loud)人名；(英)劳德"
  },
  {
    "序号": 3446,
    "单词": "shoe",
    "音标": "/ʃuː/",
    "释义": "n. 鞋；蹄铁；外胎vt. 给……穿上鞋；穿……鞋n. (Shoe)人名；(英)休"
  },
  {
    "序号": 3662,
    "单词": "staff",
    "音标": "/stæf/",
    "释义": "n.棒,杖,杆,支柱,全体职员,[军]参谋机构,[音]五线谱vt.供给人员,充当职员"
  },
  {
    "序号": 3548,
    "单词": "snowstorm",
    "音标": "/ˈsnoʊstɔːrm/",
    "释义": "n. 暴风雪；雪暴"
  },
  {
    "序号": 3642,
    "单词": "spontaneous",
    "音标": "/spɑːnˈteɪniəs/",
    "释义": "adj. 自发的；自然的；无意识的"
  },
  {
    "序号": 758,
    "单词": "compete",
    "音标": "/kəmˈpiːt/",
    "释义": "vi. 竞争；比赛；对抗"
  },
  {
    "序号": 933,
    "单词": "cube",
    "音标": "/kjuːb/",
    "释义": "n. 立方；立方体；骰子vt. 使成立方形；使自乘二次；量…的体积n. (Cube)人名；(瑞典、德)库贝"
  },
  {
    "序号": 3706,
    "单词": "sting",
    "音标": "/stɪŋ/",
    "释义": "n. 刺痛；讽刺，刺激；刺毛vt. 刺；驱使；使…苦恼；使…疼痛vi. 刺痛；被刺痛；感到剧痛n. (Sting)人名；(英)斯廷；(德)施廷"
  },
  {
    "序号": 4277,
    "单词": "wash",
    "音标": "/wɑːʃ/",
    "释义": "n.洗,洗涤,冲洗,洗涤剂,洼地,洗的衣服,冲积物vt.洗,洗涤,洗清,粉刷,冲出,弄湿,流过,镀金于vi.洗涤,洗澡,被冲蚀,漂浮adj.耐洗的,(证券交易)虚假的"
  },
  {
    "序号": 1795,
    "单词": "hay",
    "音标": "/heɪ/",
    "释义": "n. 干草vt. 把晒干vi. 割草晒干"
  },
  {
    "序号": 619,
    "单词": "chapter",
    "音标": "/ˈtʃæptər/",
    "释义": "n. 章，回；（俱乐部、协会等的）分会；人生或历史上的重要时期vt. 把…分成章节"
  },
  {
    "序号": 910,
    "单词": "credit",
    "音标": "/ˈkredɪt/",
    "释义": "n. 信用，信誉；[金融] 贷款；学分；信任；声望vt. 相信，信任；把…归给，归功于；赞颂"
  },
  {
    "序号": 2028,
    "单词": "interest",
    "音标": "/ˈɪntrəst/",
    "释义": "n. 兴趣，爱好；利息；利益；趣味；同行vt. 使……感兴趣；引起……的关心；使……参与"
  },
  {
    "序号": 301,
    "单词": "bad",
    "音标": "/bæd/",
    "释义": "adj. 坏的；严重的；劣质的n. 坏事；坏人adv. 很，非常；坏地；邪恶地n. (Bad)人名；(罗)巴德"
  },
  {
    "序号": 4128,
    "单词": "understand",
    "音标": "/ˌʌndərˈstænd/",
    "释义": "vt. 理解；懂；获悉；推断；省略；明白vi. 理解；懂得；熟悉"
  },
  {
    "序号": 2942,
    "单词": "proportional",
    "音标": "/prəˈpɔːrʃənl/",
    "释义": "adj. 比例的，成比例的；相称的，均衡的n. [数] 比例项"
  },
  {
    "序号": 2201,
    "单词": "length",
    "音标": "/leŋkθ/",
    "释义": "n. 长度，长；时间的长短；语音长"
  },
  {
    "序号": 144,
    "单词": "amount",
    "音标": "/əˈmaʊnt/",
    "释义": "n. 数量，数额；总数；（感情、特质的）程度v. 总计，合计；等于，相当于；发展成，变成"
  },
  {
    "序号": 2387,
    "单词": "memorial",
    "音标": "/məˈmɔːriəl/",
    "释义": "n. 纪念碑，纪念馆；纪念仪式；纪念物adj. 记忆的；纪念的，追悼的"
  },
  {
    "序号": 191,
    "单词": "application",
    "音标": "/ˌæplɪˈkeɪʃn/",
    "释义": "n. 应用；申请；应用程序；敷用；（对事物、学习等）投入"
  },
  {
    "序号": 2450,
    "单词": "mobile",
    "音标": "/ˈmoʊbl/",
    "释义": "adj. 可移动的；机动的；易变的；非固定的n. 移动电话"
  },
  {
    "序号": 461,
    "单词": "break",
    "音标": "/breɪk/",
    "释义": "n.休息,暂停,破裂,突变v.打破,违犯,折断,削弱,超过,突变"
  },
  {
    "序号": 2963,
    "单词": "pudding",
    "音标": "/ˈpʊdɪŋ/",
    "释义": "n. 布丁"
  },
  {
    "序号": 3332,
    "单词": "scene",
    "音标": "/siːn/",
    "释义": "n. 场面；情景；景象；事件"
  },
  {
    "序号": 1515,
    "单词": "float",
    "音标": "/floʊt/",
    "释义": "n.漂流物,浮舟,漂浮,浮萍,彩车vi.浮动,飘浮,散播,摇摆,漂浮,动摇(计划等)付诸实行vt.使漂浮,容纳,淹没,发行,实行,用水注满"
  },
  {
    "序号": 1486,
    "单词": "final",
    "音标": "/ˈfaɪnl/",
    "释义": "adj. 最终的；决定性的；不可更改的n. 决赛；期末考试；当日报纸的末版"
  },
  {
    "序号": 1115,
    "单词": "disposal",
    "音标": "/dɪˈspoʊzl/",
    "释义": "n. 处理；支配；清理；安排"
  },
  {
    "序号": 664,
    "单词": "circuit",
    "音标": "/ˈsɜːrkɪt/",
    "释义": "n. [电子] 电路，回路；巡回；一圈；环道vi. 环行vt. 绕回…环行"
  },
  {
    "序号": 2025,
    "单词": "intention",
    "音标": "/ɪnˈtenʃn/",
    "释义": "n. 意图；目的；意向；愈合"
  },
  {
    "序号": 423,
    "单词": "boil",
    "音标": "/bɔɪl/",
    "释义": "n.沸点,沸腾,疖子v.煮沸,激动"
  },
  {
    "序号": 2368,
    "单词": "meanwhile",
    "音标": "/ˈmiːnwaɪl/",
    "释义": "adv. 同时，其间n. 其间，其时"
  },
  {
    "序号": 121,
    "单词": "allow",
    "音标": "/əˈlaʊ/",
    "释义": "vt. 允许；给予；认可vi. 容许；考虑"
  },
  {
    "序号": 3512,
    "单词": "skillful",
    "音标": "/ˈskɪlfl/",
    "释义": "adj. 熟练的；巧妙的"
  },
  {
    "序号": 3900,
    "单词": "tenth",
    "音标": "/tenθ/",
    "释义": "num. 第十n. 第十个；十分之一；十度音adj. 第十个的；十分之一的"
  }
]