[
  {
    "序号": 2430,
    "单词": "minor",
    "音标": "/ˈmaɪnər/",
    "释义": "adj. 未成年的；次要的；较小的；小调的；二流的n. 未成年人；小调；辅修科目vi. 辅修n. (Minor)人名；(英)迈纳；(德、法、波、俄)米诺尔"
  },
  {
    "序号": 4105,
    "单词": "type",
    "音标": "/taɪp/",
    "释义": "n. 类型，品种；模范；样式vt. 打字；测定（血等）类型vi. 打字n. (Type)人名；(英)泰普"
  },
  {
    "序号": 2338,
    "单词": "married",
    "音标": "/ˈmærid/",
    "释义": "adj. 已婚的，有配偶的；婚姻的，夫妇的；密切结合的n. 已婚者v. 结婚，与…结婚（marry的过去式）"
  },
  {
    "序号": 2433,
    "单词": "minute",
    "音标": "/ˈmɪnɪt/",
    "释义": "n. 分，分钟；片刻，一会儿；备忘录，笔记；会议记录vt. 将……记录下来adj. 微小的，详细的"
  },
  {
    "序号": 908,
    "单词": "creative",
    "音标": "/kriˈeɪtɪv/",
    "释义": "adj. 创造性的"
  },
  {
    "序号": 2704,
    "单词": "outdoors",
    "音标": "/ˌaʊtˈdɔːrz/",
    "释义": "adv. 在户外n. 户外adj. 户外的（等于outdoor）"
  },
  {
    "序号": 2331,
    "单词": "marble",
    "音标": "/ˈmɑːrbl/",
    "释义": "n. 大理石；大理石制品；弹珠adj. 大理石的；冷酷无情的n. (Marble)人名；(英)马布尔"
  },
  {
    "序号": 948,
    "单词": "curve",
    "音标": "/kɜːrv/",
    "释义": "n. 曲线；弯曲；曲线球；曲线图表vt. 弯；使弯曲vi. 成曲形adj. 弯曲的；曲线形的"
  },
  {
    "序号": 2360,
    "单词": "mayor",
    "音标": "/ˈmeɪər/",
    "释义": "n. 市长n. (Mayor)人名；(英)梅厄；(法、西、俄)马约尔"
  },
  {
    "序号": 2610,
    "单词": "nut",
    "音标": "/nʌt/",
    "释义": "n. 螺母，螺帽；坚果；难对付的人，难解的问题vi. 采坚果n. (Nut)人名；(阿拉伯)努特；(柬)努"
  },
  {
    "序号": 1679,
    "单词": "goat",
    "音标": "/goʊt/",
    "释义": "n. 山羊；替罪羊（美俚）；色鬼（美俚）"
  },
  {
    "序号": 3391,
    "单词": "separately",
    "音标": "/ˈseprətli/",
    "释义": "adv. 分别地；分离地；个别地"
  },
  {
    "序号": 526,
    "单词": "cafe",
    "音标": "/kæˈfeɪ/",
    "释义": "n. 咖啡馆；小餐馆"
  },
  {
    "序号": 1026,
    "单词": "dependent",
    "音标": "/dɪˈpendənt/",
    "释义": "adj. 依靠的；从属的；取决于…的n. 依赖他人者；受赡养者"
  },
  {
    "序号": 3139,
    "单词": "remarkable",
    "音标": "/rɪˈmɑːrkəbl/",
    "释义": "adj. 卓越的；非凡的；值得注意的"
  },
  {
    "序号": 1340,
    "单词": "evolve",
    "音标": "/ɪˈvɑːlv/",
    "释义": "vt. 发展；进化；使逐步形成；推断出vi. 发展，进展；进化；逐步形成"
  },
  {
    "序号": 208,
    "单词": "argument",
    "音标": "/ˈɑːrɡjumənt/",
    "释义": "n. 论证；论据；争吵；内容提要；数，逻自变数；语言学主词，受词"
  },
  {
    "序号": 1877,
    "单词": "hostess",
    "音标": "/ˈhoʊstəs/",
    "释义": "n. 女主人，女老板；女服务员；舞女；女房东"
  },
  {
    "序号": 150,
    "单词": "ancestor",
    "音标": "/ˈænsestər/",
    "释义": "n. 始祖，祖先；被继承人"
  },
  {
    "序号": 1596,
    "单词": "from",
    "音标": "/frəm,frʌm,frɑːm/",
    "释义": " prep.从,今后,来自,由于"
  },
  {
    "序号": 2030,
    "单词": "interfere",
    "音标": "/ˌɪntərˈfɪr/",
    "释义": "vi. 干涉；妨碍；打扰vt. 冲突；介入"
  },
  {
    "序号": 2793,
    "单词": "plug",
    "音标": "/plʌɡ/",
    "释义": "n. 插头；塞子；栓vi. 塞住；用插头将与电源接通vt. 插入；塞住；接插头"
  },
  {
    "序号": 368,
    "单词": "beloved",
    "音标": "/bɪ'lʌvɪd/",
    "释义": "adj. 心爱的；挚爱的n. 心爱的人；亲爱的教友"
  },
  {
    "序号": 2159,
    "单词": "laser",
    "音标": "/ˈleɪzər/",
    "释义": "n. 激光n. (Laser)人名；(德)拉泽"
  },
  {
    "序号": 1672,
    "单词": "glorious",
    "音标": "/ˈɡlɔːriəs/",
    "释义": "adj. 光荣的；辉煌的；极好的"
  },
  {
    "序号": 2089,
    "单词": "joke",
    "音标": "/dʒoʊk/",
    "释义": "n. 玩笑，笑话；笑柄vt. 开…的玩笑vi. 开玩笑n. (Joke)人名；(英)乔克；(塞)约凯"
  },
  {
    "序号": 3595,
    "单词": "source",
    "音标": "/sɔːrs/",
    "释义": "n. 来源；水源；原始资料n. (Source)人名；(法)苏尔斯"
  },
  {
    "序号": 444,
    "单词": "bound",
    "音标": "/baʊnd/",
    "释义": "n.跃进,跳,范围,限度adj.正要启程的,开往...去的,被束缚的,装订的v.跳跃,限制"
  },
  {
    "序号": 869,
    "单词": "cordial",
    "音标": "/ˈkɔːrdʒəl/",
    "释义": "adj. 热情友好的；由衷的；兴奋的n. 甜果汁饮料；镇定药；兴奋剂；甜香酒"
  },
  {
    "序号": 1438,
    "单词": "fast",
    "音标": "/fæst/",
    "释义": "adj. 快速的，迅速的；紧的，稳固的adv. 迅速地；紧紧地；彻底地vi. 禁食，斋戒n. 斋戒；绝食n. (Fast)人名；(德、英、俄、芬、捷、瑞典)法斯特"
  },
  {
    "序号": 3117,
    "单词": "rejoice",
    "音标": "/rɪˈdʒɔɪs/",
    "释义": "vi. 高兴；庆祝vt. 使高兴"
  },
  {
    "序号": 642,
    "单词": "chicken",
    "音标": "/ˈtʃɪkɪn/",
    "释义": "n. 鸡肉；小鸡；胆小鬼，懦夫adj. 鸡肉的；胆怯的；幼小的"
  },
  {
    "序号": 199,
    "单词": "approve",
    "音标": "/əˈpruːv/",
    "释义": "vt. 批准；赞成；为…提供证据vi. 批准；赞成；满意"
  },
  {
    "序号": 1055,
    "单词": "devil",
    "音标": "/ˈdevl/",
    "释义": "n. 魔鬼；撒旦；家伙；恶棍；淘气鬼；冒失鬼vt. 虐待，折磨；（用扯碎机）扯碎；（替作家，律师等）做助手；抹辣味料烤制或煎煮"
  },
  {
    "序号": 3385,
    "单词": "senior",
    "音标": "/ˈsiːniər/",
    "释义": "adj. 高级的；年长的；地位较高的；年资较深的，资格较老的n. 上司；较年长者；毕业班学生n. (Senior)人名；(英)西尼尔"
  },
  {
    "序号": 2795,
    "单词": "plural",
    "音标": "/ˈplʊrəl/",
    "释义": "adj. （语法）复数（形式）的；多样的n. （语法）复数（形式）；（讽）黑人"
  },
  {
    "序号": 2340,
    "单词": "marvelous",
    "音标": "/ˈmɑːrvələs/",
    "释义": "adj. 了不起的；非凡的；令人惊异的；不平常的"
  },
  {
    "序号": 809,
    "单词": "connect",
    "音标": "/kəˈnekt/",
    "释义": "vt. 连接；联合；关连；链接vi. 连接，连结；联合"
  },
  {
    "序号": 1093,
    "单词": "disappoint",
    "音标": "/ˌdɪsəˈpɔɪnt/",
    "释义": "vt. 使失望"
  },
  {
    "序号": 264,
    "单词": "attraction",
    "音标": "/əˈtrækʃn/",
    "释义": "n. 吸引，吸引力；引力；吸引人的事物"
  },
  {
    "序号": 2349,
    "单词": "mate",
    "音标": "/meɪt/",
    "释义": "n.配偶,对手,助手vt.使配对,使一致,结伴vi.成配偶,紧密配合"
  },
  {
    "序号": 63,
    "单词": "addition",
    "音标": "/əˈdɪʃn/",
    "释义": "n. 添加；[数] 加法；增加物"
  },
  {
    "序号": 1166,
    "单词": "drawing",
    "音标": "/ˈdrɔːɪŋ/",
    "释义": "n. 图画；牵引；素描术v. 绘画；吸引（draw的ing形式）；拖曳"
  },
  {
    "序号": 2500,
    "单词": "murderer",
    "音标": "/ˈmɜːrdərər/",
    "释义": "n. 凶手；谋杀犯"
  },
  {
    "序号": 1477,
    "单词": "fifteen",
    "音标": "/ˌfɪfˈtiːn/",
    "释义": "n. 十五；十五个；十五人组成的橄榄球队adj. 十五的num. 十五"
  },
  {
    "序号": 4221,
    "单词": "vest",
    "音标": "/vest/",
    "释义": "n. 背心；汗衫vt. 授予；使穿衣vi. 归属；穿衣服n. (Vest)人名；(英)维斯特；(匈)韦什特"
  },
  {
    "序号": 2616,
    "单词": "objection",
    "音标": "/əbˈdʒekʃn/",
    "释义": "n. 异议，反对；缺陷，缺点；妨碍；拒绝的理由"
  },
  {
    "序号": 123,
    "单词": "almost",
    "音标": "/ˈɔːlmoʊst/",
    "释义": "adv. 差不多，几乎"
  },
  {
    "序号": 543,
    "单词": "Canadian",
    "音标": "/kəˈneɪdiən/",
    "释义": "adj. 加拿大的；加拿大人的；加拿大文化的n. 加拿大人；加拿大河（美国河流）"
  },
  {
    "序号": 4316,
    "单词": "what",
    "音标": "/wʌt/",
    "释义": "pron. 什么；多么；多少adj. 什么；多么；何等adv. 到什么程度，在哪一方面int. 什么；多么"
  }
]